pysnapd/__init__.py
pysnapd/__main__.py
pysnapd/config.py
pysnapd/manager.py
pysnapd/snap.py
pysnapd/utils.py
pysnapd-1.0.2.dist-info/METADATA
pysnapd-1.0.2.dist-info/WHEEL
pysnapd-1.0.2.dist-info/entry_points.txt
pysnapd-1.0.2.dist-info/RECORD
