Metadata-Version: 2.1
Name: pysnapd
Version: 1.0.2
Summary: Minimal snapd-like supervisor
License: MIT
Author: Kuba Szczodrzyński
Author-email: kuba@szczodrzynski.pl
Requires-Python: >=3.10,<4.0
Classifier: License :: OSI Approved :: MIT License
Classifier: Programming Language :: Python :: 3
Classifier: Programming Language :: Python :: 3.10
Classifier: Programming Language :: Python :: 3.11
Classifier: Programming Language :: Python :: 3.12
Requires-Dist: PyYAML (>=6.0,<7.0)
Requires-Dist: click (>=8.1.3,<9.0.0)
Requires-Dist: requests (>=2.28.1,<3.0.0)
